{
  "Disabled": false,
  "Testing": false,
  "ScheduledForDeletion": false,
  "InstalledFromUrl": "https://raw.githubusercontent.com/Dalamud-Kr/DalamudPlugins/api6/pluginmaster.json",
  "IsThirdParty": false,
  "EffectiveVersion": "2.0.0.0",
  "Author": "Eternita, Chalkos",
  "Name": "QuestAWAY",
  "Punchline": "Removes unwanted icons from your map.",
  "Description": "Removes unwanted icons from your map. Not only quests, any icons.",
  "Changelog": null,
  "Tags": null,
  "CategoryTags": [
    "UI"
  ],
  "IsHide": false,
  "InternalName": "QuestAWAY",
  "AssemblyVersion": "2.0.0.0",
  "TestingAssemblyVersion": null,
  "IsTestingExclusive": false,
  "RepoUrl": "https://github.com/Eternita-S/QuestAWAY",
  "ApplicableVersion": "any",
  "DalamudApiLevel": 6,
  "DownloadCount": 28639,
  "LastUpdate": 1652946451,
  "DownloadLinkInstall": "https://raw.githubusercontent.com/Dalamud-Kr/DalamudPlugins/api6/plugins/QuestAWAY/latest.zip",
  "DownloadLinkUpdate": "https://raw.githubusercontent.com/Dalamud-Kr/DalamudPlugins/api6/plugins/QuestAWAY/latest.zip",
  "DownloadLinkTesting": "https://raw.githubusercontent.com/Dalamud-Kr/DalamudPlugins/api6/plugins/QuestAWAY/latest.zip",
  "LoadRequiredState": 0,
  "LoadSync": false,
  "LoadPriority": 0,
  "CanUnloadAsync": false,
  "ImageUrls": null,
  "IconUrl": null,
  "AcceptsFeedback": true,
  "FeedbackMessage": null,
  "_isDip17Plugin": false,
  "_Dip17Channel": null
}